MANIFEST.in
RELEASE-VERSION
get_git_version.py
setup.py
src/__init__.py
src/cnczPush.py
src/cometApi.py
src/mirror.py
src/ruuster.py
src/sqlite3History.py
src/state.py
src/./base.mirte
src/./cnczPush.mirte
src/./cometApi.mirte
src/./default.mirte
src/./mirror.mirte
src/./ruuster.mirte
src/./sqlite3History.mirte
src/./state.mirte
src/./setups/default.mirte
src/./setups/slave.mirte
test/test-push.py
tkbd.egg-info/PKG-INFO
tkbd.egg-info/SOURCES.txt
tkbd.egg-info/dependency_links.txt
tkbd.egg-info/not-zip-safe
tkbd.egg-info/requires.txt
tkbd.egg-info/top_level.txt