Metadata-Version: 1.0
Name: tkbd
Version: 0.3.8
Summary: Terminal Kamer Bezetting Daemon voor de faculteit NWI van de Radboud Universiteit
Home-page: http://github.com/bwesterb/tkbd
Author: Bas Westerbaan
Author-email: bas@westerbaan.name
License: UNKNOWN
Platform: UNKNOWN
